CFsshTunnel/CFsshTunnel.py
CFsshTunnel/__init__.py
CFsshTunnel/cloudflare/__init__.py
CFsshTunnel/cloudflare/cloudflare.py
CFsshTunnel/cloudflare/cloudflare_config.py
CFsshTunnel/code_server/__init__.py
CFsshTunnel/code_server/code_server.py
CFsshTunnel/ssh/__init__.py
CFsshTunnel/ssh/ssh.py
CFsshTunnel/ssh/ssh_config.py
CFsshTunnel/utils/__init__.py
CFsshTunnel/utils/decorated_print.py
CFsshTunnel/utils/package_installer.py
CFsshTunnel/utils/utils.py
CFsshTunnel-0.2.1.dist-info/LICENSE
CFsshTunnel-0.2.1.dist-info/METADATA
CFsshTunnel-0.2.1.dist-info/WHEEL
CFsshTunnel-0.2.1.dist-info/top_level.txt
CFsshTunnel-0.2.1.dist-info/RECORD
