Metadata-Version: 2.1
Name: CFsshTunnel
Version: 0.2.1
Summary: Cloudflare Tunnel for open-ssh and code-server
Home-page: https://github.com/ThePilot916/CFsshTunnel.git
License: MIT
Keywords: SSH,Tunnel,Cloudflare,colab_ssh,aws,aws_ssh,code-server,remote developmentvscode_server,vscode_remote,google colab
Platform: UNKNOWN
Classifier: Intended Audience :: Developers
Classifier: Topic :: Software Development :: Build Tools
Classifier: License :: OSI Approved :: MIT License
Classifier: Programming Language :: Python :: 3.5
Requires-Dist: python-apt
